tencentcloud/__init__.py
tencentcloud/tione/__init__.py
tencentcloud/tione/v20191022/__init__.py
tencentcloud/tione/v20191022/errorcodes.py
tencentcloud/tione/v20191022/models.py
tencentcloud/tione/v20191022/tione_client.py
tencentcloud/tione/v20191022/tione_client_async.py
tencentcloud/tione/v20211111/__init__.py
tencentcloud/tione/v20211111/errorcodes.py
tencentcloud/tione/v20211111/models.py
tencentcloud/tione/v20211111/tione_client.py
tencentcloud/tione/v20211111/tione_client_async.py
tencentcloud_sdk_python_tione-3.1.35.dist-info/METADATA
tencentcloud_sdk_python_tione-3.1.35.dist-info/WHEEL
tencentcloud_sdk_python_tione-3.1.35.dist-info/top_level.txt
tencentcloud_sdk_python_tione-3.1.35.dist-info/RECORD
